modelcar_base_image/__init__.py
modelcar_base_image/constants.py
modelcar_base_image/embedded_oci_layout/blobs/sha256/05dc61989ecd85e85b13d6dd28f732cedb9cd6e086bd15e6e48ba53e90061c39
modelcar_base_image/embedded_oci_layout/blobs/sha256/154c53af920fdb3cc9ddc1a0717fb531c28c2efcb91707f509d271aac3d3e680
modelcar_base_image/embedded_oci_layout/blobs/sha256/52a45566354fc688d802b1c48b0f86f9760e235ca06655f83429956cd802c39e
modelcar_base_image/embedded_oci_layout/blobs/sha256/67c4b54559a7a3b84ca9bde8acde0e93e1dc07f498a61a69812b5bb89f59308b
modelcar_base_image/embedded_oci_layout/blobs/sha256/a2c2e243bbfb07ca76921cbb5ab25bc38c61bd1ca0aae1eda0408a08d703ea41
modelcar_base_image/embedded_oci_layout/blobs/sha256/cda2d1a588b1ecea65a734790c5ace3677b6e63d3686006368e758186485ef10
modelcar_base_image/embedded_oci_layout/blobs/sha256/de04b769cc31b4bda312f9c7f523b73102b1309d17b83f76f42d425af120d853
modelcar_base_image/embedded_oci_layout/index.json
modelcar_base_image/embedded_oci_layout/oci-layout
modelcar_base_image/embedded_oci_layout.py
modelcar_base_image/prepare.py
modelcar_base_image/py.typed
modelcar_base_image-0.1.0.dist-info/WHEEL
modelcar_base_image-0.1.0.dist-info/METADATA
modelcar_base_image-0.1.0.dist-info/RECORD
