Metadata-Version: 2.3
Name: modelcar-base-image
Version: 0.1.0
Summary: A minimal base image for KServe Modelcar/sidecar
Author: tarilabs
Author-email: tarilabs <matteo.mortari@gmail.com>
Requires-Dist: pytest>=7.0.0 ; extra == 'dev'
Requires-Python: >=3.9
Provides-Extra: dev
